MANIFEST.in
README.txt
setup.cfg
setup.py
docs/CREDITS.txt
docs/HISTORY.txt
docs/INSTALL.txt
docs/LICENSE.GPL
docs/LICENSE.txt
src/collective/__init__.py
src/collective.twitter.tweet.egg-info/PKG-INFO
src/collective.twitter.tweet.egg-info/SOURCES.txt
src/collective.twitter.tweet.egg-info/dependency_links.txt
src/collective.twitter.tweet.egg-info/entry_points.txt
src/collective.twitter.tweet.egg-info/namespace_packages.txt
src/collective.twitter.tweet.egg-info/not-zip-safe
src/collective.twitter.tweet.egg-info/requires.txt
src/collective.twitter.tweet.egg-info/top_level.txt
src/collective/twitter/__init__.py
src/collective/twitter/tweet/__init__.py
src/collective/twitter/tweet/config.py
src/collective/twitter/tweet/configure.zcml
src/collective/twitter/tweet/content.py
src/collective/twitter/tweet/interfaces.py
src/collective/twitter/tweet/setuphandlers.py
src/collective/twitter/tweet/testing.py
src/collective/twitter/tweet/locales/collective.twitter.tweet.pot
src/collective/twitter/tweet/locales/es/LC_MESSAGES/collective.twitter.tweet.po
src/collective/twitter/tweet/profiles/default/collective.twitter.tweet_various.txt
src/collective/twitter/tweet/profiles/default/metadata.xml
src/collective/twitter/tweet/profiles/initial/metadata.xml
src/collective/twitter/tweet/tests/__init__.py
src/collective/twitter/tweet/tests/test_action_tweet.py
src/collective/twitter/tweet/tests/test_setup.py