Metadata-Version: 1.0
Name: collective.twitter.tweet
Version: 1.0b2
Summary: This product provides different twitter actions to be used with content rules.
Home-page: https://github.com/collective/collective.twitter.tweet
Author: Franco Pellegrini
Author-email: frapell@ravvit.net
License: GPL
Keywords: plone twitter action tweet shorten
Platform: UNKNOWN
Classifier: Development Status :: 4 - Beta
Classifier: Environment :: Web Environment
Classifier: Framework :: Plone
Classifier: Framework :: Plone :: 4.1
Classifier: Framework :: Plone :: 4.2
Classifier: Intended Audience :: System Administrators
Classifier: License :: OSI Approved :: GNU General Public License (GPL)
Classifier: Operating System :: OS Independent
Classifier: Programming Language :: JavaScript
Classifier: Programming Language :: Python
Classifier: Programming Language :: Python :: 2.6
Classifier: Programming Language :: Python :: 2.7
Classifier: Topic :: Software Development :: Libraries :: Python Modules
